TorScrape/__init__.py
TorScrape/instaData.py
TorScrape/tiktokData.py
torscrape-0.1.22.dist-info/LICENSE
torscrape-0.1.22.dist-info/METADATA
torscrape-0.1.22.dist-info/WHEEL
torscrape-0.1.22.dist-info/top_level.txt
torscrape-0.1.22.dist-info/RECORD
