Metadata-Version: 2.1
Name: torscrape
Version: 0.1.22
Summary: A webscrape package
Home-page: https://github.com/toreofc/TorScrape/
Author: Tore.ofc, rxality
Author-email: tore.ofc.99@gmail.com
Project-URL: Bug Tracker, https://github.com/toreofc/TorScrape/issues
Classifier: Programming Language :: Python :: 3
Classifier: License :: OSI Approved :: MIT License
Classifier: Operating System :: OS Independent
Requires-Python: >=3.6
License-File: LICENSE
Requires-Dist: requests
Requires-Dist: beautifulsoup4
Requires-Dist: aiohttp
